el0ps/__init__.py
el0ps/compilation.py
el0ps/path.py
el0ps/utils.py
el0ps/datafit/__init__.py
el0ps/datafit/base.py
el0ps/datafit/kullbackleibler.py
el0ps/datafit/leastsquares.py
el0ps/datafit/logcosh.py
el0ps/datafit/logistic.py
el0ps/datafit/squaredhinge.py
el0ps/estimator/__init__.py
el0ps/estimator/base.py
el0ps/estimator/classifier.py
el0ps/estimator/regressor.py
el0ps/estimator/svc.py
el0ps/estimator/utils.py
el0ps/penalty/__init__.py
el0ps/penalty/base.py
el0ps/penalty/bigm.py
el0ps/penalty/bigml1norm.py
el0ps/penalty/bigml2norm.py
el0ps/penalty/bigmpositivel1norm.py
el0ps/penalty/bigmpositivel2norm.py
el0ps/penalty/bounds.py
el0ps/penalty/l1l2norm.py
el0ps/penalty/l1norm.py
el0ps/penalty/l2norm.py
el0ps/penalty/positivel1norm.py
el0ps/penalty/positivel2norm.py
el0ps/solver/__init__.py
el0ps/solver/base.py
el0ps/solver/bnb.py
el0ps/solver/mip.py
el0ps/solver/oa.py
el0ps-0.0.3.dist-info/licenses/LICENSE
el0ps-0.0.3.dist-info/METADATA
el0ps-0.0.3.dist-info/WHEEL
el0ps-0.0.3.dist-info/top_level.txt
el0ps-0.0.3.dist-info/RECORD
