Metadata-Version: 2.4
Name: el0ps
Version: 0.0.3
Summary: An Exact L0-Problem Solver
Author-email: Théo Guyard <theo.guyard.job@gmail.com>
License:                     GNU GENERAL PUBLIC LICENSE
Project-URL: Homepage, https://github.com/TheoGuyard/El0ps
Project-URL: Bug Reports, https://github.com/TheoGuyard/El0ps/issues
License-File: LICENSE
Requires-Dist: mpi4py
Requires-Dist: numpy
Requires-Dist: numba
Requires-Dist: pybnb
Requires-Dist: pyomo
Requires-Dist: scikit-learn
Provides-Extra: mip
Requires-Dist: cplex; extra == "mip"
Requires-Dist: docplex; extra == "mip"
Requires-Dist: gurobipy; extra == "mip"
Requires-Dist: Mosek; extra == "mip"
Provides-Extra: dev
Requires-Dist: black; extra == "dev"
Requires-Dist: build; extra == "dev"
Requires-Dist: coverage; extra == "dev"
Requires-Dist: flake8; extra == "dev"
Requires-Dist: furo; extra == "dev"
Requires-Dist: numpydoc; extra == "dev"
Requires-Dist: pydoctest; extra == "dev"
Requires-Dist: pytest; extra == "dev"
Requires-Dist: sphinx; extra == "dev"
Requires-Dist: sphinx_autodoc_typehints; extra == "dev"
Requires-Dist: sphinx_copybutton; extra == "dev"
Requires-Dist: sphinx-prompt; extra == "dev"
Requires-Dist: twine; extra == "dev"
Requires-Dist: wheel; extra == "dev"
Dynamic: license-file
